bstree.cp312-win_amd64.pyd
bstree-0.8.dist-info/LICENSE
bstree-0.8.dist-info/METADATA
bstree-0.8.dist-info/WHEEL
bstree-0.8.dist-info/top_level.txt
bstree-0.8.dist-info/RECORD
